{
  "required": true,
  "minVersion": "0.8",
  "package": "com.teammoeg.frostedheart.mixin",
  "compatibilityLevel": "JAVA_8",
  "refmap": "frostedheart.refmap.json",
  "mixins": [
    "immersiveengineering.HempBlockMixin",
    "jei.MixinCommandUtilServer",
    "minecraft.BiomeMixin",
    "minecraft.CampfireBlockMixin",
    "minecraft.CampfireTileEntityMixin",
    "minecraft.IceMixin",
    "minecraft.PortalSizeMixin",
    "minecraft.VillagerMixin",
    "minecraft.MixinServerWorld",
    "minecraft.BeeHiveMixin",
    "minecraft.BigTreeMixin",
    "minecraft.MixinSwampHutPiece",
    "primalwinter.WeatherDataAccess",
    "primalwinter.WeatherDataMixin",
    "projecte.MixinPhilosopherStone",
    "projecte.MixinTransmutationStone",
    "projecte.MixinTransmutationTablet",
    "rankine.AlloyTemplateItemMixin",
    "rankine.TapBarrelBlockMixin",
    "rankine.MixinDryMortarItemEntity",
    "rankine.MixinEHTree",
    "rankine.MixinPPTree",
    "snow.ModSnowBlockMixin",
    "snow.ModUtilMixin",
    "create.MixinProcessingScenes",
    "create.MixinSmartTileEntity",
    "create.MixinGantryShaftTileEntity",
    "create.MixinGantryContraptionEntity",
    "create.MixinCartAssemblerTileEntity",
    "create.HandCrankBlockMixin",
    "create.MixinAbstractContraption",
    "create.MixinPulleyTileEntity",
    "create.MixinClockworkBearingTileEntity",
    "create.MixinMechanicalBearingTileEntity",
    "forge.FluidHandlerItemStackMixin",
    "forge.FluidHandlerItemStackSimpleMixin"
  ],
  "client": [
    "client.ForgeIngameGuiMixin",
    "client.IngameGuiAccess",
    "client.IngameGuiMixin",
    "client.ToastGuiMixin",
    "client.MixinClientEvents",
    "rankine.MixinDryMortarItem",
    "rankine.MixinMortarItem"
  ],
  "injectors": {
    "defaultRequire": 1
  }
}
