{
  "required": true,
  "minVersion": "0.8",
  "package": "com.teammoeg.frostedheart.mixin",
  "compatibilityLevel": "JAVA_8",
  "mixins": [
    "immersiveengineering.HempBlockMixin",
    "jei.MixinCommandUtilServer",
    "minecraft.BiomeMixin",
    "minecraft.CampfireBlockMixin",
    "minecraft.CampfireTileEntityMixin",
    "minecraft.IceMixin",
    "minecraft.PortalSizeMixin",
    "minecraft.SnowMixin",
    "primalwinter.WeatherDataAccess",
    "primalwinter.WeatherDataMixin",
    "rankine.AlloyTemplateItemMixin",
    "snow.ModSnowBlockMixin",
    "snow.ModUtilMixin"
  ],
  "client": [
  ],
  "injectors": {
    "defaultRequire": 1
  }
}
